tidy/__init__.py
tidy/error.py
tidy/lib.py
tidy/py.typed
tidy/test_tidy.py
tidy/test_data/test.html
utidylib-1.0.0.dist-info/licenses/LICENSE
utidylib-1.0.0.dist-info/METADATA
utidylib-1.0.0.dist-info/WHEEL
utidylib-1.0.0.dist-info/top_level.txt
utidylib-1.0.0.dist-info/RECORD
