Metadata-Version: 2.4
Name: uTidylib
Version: 1.0.0
Summary: Wrapper for HTML Tidy
Author-email: Michal Čihař <michal@cihar.com>
License-Expression: MIT
Project-URL: Documentation, https://utidylib.readthedocs.io/
Project-URL: Download, https://github.com/nijel/utidylib
Project-URL: Funding, https://liberapay.com/nijel
Project-URL: Homepage, https://github.com/nijel/utidylib
Project-URL: Issue Tracker, https://github.com/nijel/utidylib/issues
Project-URL: Source Code, https://github.com/nijel/utidylib
Classifier: Development Status :: 5 - Production/Stable
Classifier: Environment :: Web Environment
Classifier: Intended Audience :: Developers
Classifier: Programming Language :: Python :: 3 :: Only
Classifier: Programming Language :: Python :: 3
Classifier: Programming Language :: Python :: 3.10
Classifier: Programming Language :: Python :: 3.11
Classifier: Programming Language :: Python :: 3.12
Classifier: Programming Language :: Python :: 3.13
Classifier: Programming Language :: Python :: 3.14
Classifier: Programming Language :: Python
Classifier: Topic :: Internet
Requires-Python: >=3.10
License-File: LICENSE
Dynamic: license-file
